pyblox3/__init__.py
pyblox3/api/assets.py
pyblox3/api/friends.py
pyblox3/api/groups.py
pyblox3/api/http.py
pyblox3/api/user.py
pyblox3-2.4.4.dist-info/LICENSE
pyblox3-2.4.4.dist-info/METADATA
pyblox3-2.4.4.dist-info/WHEEL
pyblox3-2.4.4.dist-info/top_level.txt
pyblox3-2.4.4.dist-info/RECORD
