Metadata-Version: 2.1
Name: pyblox3
Version: 2.4.4
Summary: An API wrapper for Roblox written in Python.
Home-page: https://github.com/RbxAPI/Pyblox/tree/master
Author: Sanjay-B (Sanjay Bhadra)
Author-email: sanjay2003rbx@gmail.com
License: UNKNOWN
Platform: UNKNOWN
Classifier: Programming Language :: Python :: 3
Classifier: License :: OSI Approved :: MIT License
Classifier: Operating System :: OS Independent
Requires-Python: >=3.5
